BoardRender/BR.py
BoardRender/__init__.py
BoardRender-0.1.4.dist-info/METADATA
BoardRender-0.1.4.dist-info/WHEEL
BoardRender-0.1.4.dist-info/top_level.txt
BoardRender-0.1.4.dist-info/RECORD
